onerouter/__init__.py
onerouter/client.py
onerouter/communications.py
onerouter/exceptions.py
onerouter/http_client.py
onerouter/utils.py
onerouter/resources/__init__.py
onerouter/resources/marketplace.py
onerouter/resources/payment_links.py
onerouter/resources/payments.py
onerouter/resources/saved_payment_methods.py
onerouter/resources/subscriptions.py
onerouter-2.0.1.dist-info/licenses/LICENSE
onerouter-2.0.1.dist-info/METADATA
onerouter-2.0.1.dist-info/WHEEL
onerouter-2.0.1.dist-info/top_level.txt
onerouter-2.0.1.dist-info/RECORD
