Metadata-Version: 2.4
Name: onerouter
Version: 2.0.1
Summary: Unified API client for payments, subscriptions, SMS, email, and marketplace features
Home-page: https://github.com/onerouter/onerouter-python
Author: OneRouter Team
Author-email: OneRouter Team <support@onerouter.com>
License: MIT
Project-URL: Homepage, https://onerouter.com
Project-URL: Documentation, https://docs.onerouter.com
Project-URL: Repository, https://github.com/onerouter/onerouter-python
Project-URL: Changelog, https://github.com/onerouter/onerouter-python/blob/main/CHANGELOG.md
Keywords: payments,razorpay,paypal,stripe,unified-api
Classifier: Development Status :: 4 - Beta
Classifier: Intended Audience :: Developers
Classifier: License :: OSI Approved :: MIT License
Classifier: Programming Language :: Python :: 3
Classifier: Programming Language :: Python :: 3.8
Classifier: Programming Language :: Python :: 3.9
Classifier: Programming Language :: Python :: 3.10
Classifier: Programming Language :: Python :: 3.11
Classifier: Programming Language :: Python :: 3.12
Requires-Python: >=3.8
License-File: LICENSE
Requires-Dist: httpx>=0.25.0
Provides-Extra: dev
Requires-Dist: pytest>=7.0.0; extra == "dev"
Requires-Dist: pytest-asyncio>=0.21.0; extra == "dev"
Requires-Dist: pytest-cov>=4.0.0; extra == "dev"
Requires-Dist: black>=23.0.0; extra == "dev"
Requires-Dist: mypy>=1.0.0; extra == "dev"
Dynamic: author
Dynamic: home-page
Dynamic: license-file
Dynamic: requires-python
